openfv/__init__.py
openfv/main.py
openfv-0.3.6.dist-info/METADATA
openfv-0.3.6.dist-info/WHEEL
openfv-0.3.6.dist-info/top_level.txt
openfv-0.3.6.dist-info/RECORD
