Metadata-Version: 2.2
Name: openfv
Version: 0.3.6
Summary: computer vision packages in frequency domain
Home-page: https://github.com/bemoregt/openfv
Author: Wonwoo Park
Author-email: bemore.one@gmail.com
Classifier: Programming Language :: Python :: 3
Classifier: License :: OSI Approved :: MIT License
Requires-Python: >=3.10
Requires-Dist: numpy
Requires-Dist: scipy
Requires-Dist: opencv-python
Dynamic: author
Dynamic: author-email
Dynamic: classifier
Dynamic: description
Dynamic: description-content-type
Dynamic: home-page
Dynamic: requires-dist
Dynamic: requires-python
Dynamic: summary
